{
  "requestsFinished": 1,
  "requestsFailed": 0,
  "requestsRetries": 0,
  "requestsFailedPerMinute": 0,
  "requestsFinishedPerMinute": 10,
  "requestMinDurationMillis": 5048,
  "requestMaxDurationMillis": 5048,
  "requestTotalFailedDurationMillis": 0,
  "requestTotalFinishedDurationMillis": 5048,
  "crawlerStartedAt": "2026-06-16T08:09:05.276Z",
  "crawlerFinishedAt": "2026-06-16T08:09:11.275Z",
  "statsPersistedAt": "2026-06-16T08:09:11.275Z",
  "crawlerRuntimeMillis": 6160,
  "crawlerLastStartTimestamp": 1781597345115,
  "requestRetryHistogram": [
    1
  ],
  "statsId": 10,
  "requestAvgFailedDurationMillis": null,
  "requestAvgFinishedDurationMillis": 5048,
  "requestTotalDurationMillis": 5048,
  "requestsTotal": 1,
  "requestsWithStatusCode": {
    "200": 1
  },
  "errors": {},
  "retryErrors": {}
}